<DOMSymbolItem xmlns:xsi="http://www.w3.org/2001/XMLSchema-instance" xmlns="http://ns.adobe.com/xfl/2008/" name="Assets/FullBottles/SodaBottle_Plain" itemID="5abe4f0d-000011d1" lastModified="1528814399">
  <timeline>
    <DOMTimeline name="SodaBottle_Plain">
      <layers>
        <DOMLayer name="Layer_1" color="#00FFFF" current="true" isSelected="true">
          <frames>
            <DOMFrame index="0" keyMode="9728">
              <elements>
                <DOMShape>
                  <fills>
                    <FillStyle index="1">
                      <RadialGradient>
                        <matrix>
                          <Matrix a="0.0504150390625" d="0.0504150390625" tx="1.7" ty="-68.4"/>
                        </matrix>
                        <GradientEntry color="#00A7FF" ratio="0"/>
                        <GradientEntry color="#DFF3FF" ratio="0"/>
                        <GradientEntry color="#D0EEFF" alpha="0.0470588235294118" ratio="0.00784313725490196"/>
                        <GradientEntry color="#FFFFFF" ratio="1"/>
                      </RadialGradient>
                    </FillStyle>
                    <FillStyle index="2">
                      <RadialGradient>
                        <matrix>
                          <Matrix a="0.0504150390625" d="0.0504150390625" tx="-0.3" ty="-68.4"/>
                        </matrix>
                        <GradientEntry color="#00A7FF" ratio="0"/>
                        <GradientEntry color="#DFF3FF" ratio="0"/>
                        <GradientEntry color="#D0EEFF" alpha="0.0470588235294118" ratio="0.00784313725490196"/>
                        <GradientEntry color="#FFFFFF" ratio="1"/>
                      </RadialGradient>
                    </FillStyle>
                  </fills>
                  <strokes>
                    <StrokeStyle index="1">
                      <SolidStroke scaleMode="normal" weight="0.1">
                        <fill>
                          <SolidColor/>
                        </fill>
                      </SolidStroke>
                    </StrokeStyle>
                  </strokes>
                  <edges>
                    <Edge fillStyle0="1" edges="!113 -2047[104 -2047 96 -2047!96 -2047|-89 -2045!-89 -2045[-90 -2043 -91 -2042!-91 -2042[-109 -2005 -152 -1998!-152 -1998[-143 -1993 -129 -1992!-129 -1992[-120 -1992 -103 -1992!-103 -1992[-96 -1991 -54 -1978!-54 -1978[-35 -1973 21 -1969
!21 -1969[81 -1966 178 -1947!178 -1947[190 -1945 200 -1942!200 -1942|210 -2022!210 -2022[170 -2042 113 -2047"/>
                    <Edge fillStyle0="2" edges="
!433 -734|416 -790!416 -790[414 -784 409 -779!409 -779[402 -772 393 -774!393 -774[383 -777 376 -797!376 -797[373 -806 370 -816!370 -816[363 -802 352 -790!352 -790[330 -768 304 -770!304 -770[296 -771 288 -773!288 -773[290 -758 289 -745
!289 -745[289 -732 283 -723!283 -723[276 -711 263 -714!263 -714[252 -717 250 -730!250 -730[224 -717 198 -724!198 -724[144 -737 121 -802!121 -802[108 -841 108 -915!108 -915|108 -1264!108 -1264[98 -1288 93 -1325!93 -1325[85 -1400 86 -1459
!86 -1459[89 -1577 136 -1792!136 -1792[137 -1798 139 -1804!139 -1804[120 -1806 96 -1812!96 -1812[74 -1817 54 -1820!54 -1820[5 -1821 -28 -1821!-28 -1821[-126 -1822 -213 -1825!-213 -1825[-205 -1816 -206 -1789!-206 -1789|-209 -1754!-209
 -1754[-205 -1739 -204 -1727!-204 -1727[-200 -1696 -200 -1632!-200 -1632[-198 -1601 -191 -1540!-191 -1540[-185 -1446 -212 -1332!-212 -1332[-229 -1259 -274 -1129!-274 -1129|-361 -879!-361 -879[-365 -868 -368 -858!-368 -858[-348 -858 -332
 -859!-332 -859|-331 -742!-331 -742|-453 -742!-453 -742[-264 -543 -6 -543!-6 -543[4 -543 14 -543!14 -543[254 -551 433 -734"/>
                    <Edge fillStyle0="1" edges="
!519 -1118[518 -1109 519 -1100!519 -1100|529 -1067!529 -1067|529 -1081!529 -1081[527 -1106 519 -1118"/>
                    <Edge strokeStyle="1" edges="
!473 -734[287 -543 34 -543!34 -543[24 -543 14 -543"/>
                    <Edge fillStyle0="1" edges="
!-307 -2041[-307 -2032 -303 -2020!-303 -2020[-303 -2032 -302 -2041!-302 -2041|-307 -2041!-397 -1516[-401 -1500 -404 -1484!-404 -1484[-398 -1501 -392 -1516!-392 -1516|-397 -1516"/>
                    <Edge cubics="!473 -734(;349,-607 202,-543 34,-543q473 -734Q287 -543q34 -543);"/>
                    <Edge cubics="!529 -1081(;528,-1094 526,-1108 519,-1118q529 -1081Q527 -1106q519 -1118);"/>
                    <Edge cubics="!113 -2047(;107,-2047 101,-2047 96,-2047q113 -2047Q104 -2047q96 -2047);"/>
                    <Edge cubics="!-397 -1516(;-400,-1505 -402,-1495 -404,-1484q-397 -1516Q-401 -1500q-404 -1484);"/>
                    <Edge cubics="!-404 -1484(;-400,-1495 -396,-1506 -392,-1516q-404 -1484Q-398 -1501q-392 -1516);"/>
                    <Edge cubics="!-392 -1516(;-392,-1516 -397,-1516 -397,-1516q-392 -1516 -397 -1516);"/>
                    <Edge cubics="!519 -1118(;518,-1112 518,-1106 519,-1100q519 -1118Q518 -1109q519 -1100);"/>
                    <Edge cubics="!529 -1067(;529,-1067 529,-1081 529,-1081q529 -1067 529 -1081);"/>
                    <Edge cubics="!519 -1100(;519,-1100 529,-1067 529,-1067q519 -1100 529 -1067);"/>
                    <Edge cubics="!-91 -2042(;-102,-2019 -126,-2002 -152,-1998q-91 -2042Q-109 -2005q-152 -1998);"/>
                    <Edge cubics="!-152 -1998(;-138,-1990 -120,-1993 -103,-1992q-152 -1998Q-143 -1993q-129 -1992Q-120 -1992q-103 -1992);"/>
                    <Edge cubics="!-103 -1992(;-86,-1990 -70,-1983 -54,-1978q-103 -1992Q-96 -1991q-54 -1978);"/>
                    <Edge cubics="!-54 -1978(;-29,-1972 -4,-1971 21,-1969q-54 -1978Q-35 -1973q21 -1969);"/>
                    <Edge cubics="!21 -1969(;74,-1966 126,-1957 178,-1947q21 -1969Q81 -1966q178 -1947);"/>
                    <Edge cubics="!-332 -859(;-332,-820 -332,-781 -331,-742q-332 -859 -331 -742);"/>
                    <Edge cubics="!-6 -543(;-178,-543 -327,-609 -453,-742q-6 -543Q-264 -543q-453 -742);"/>
                    <Edge cubics="!433 -734(;433,-734 416,-790 416,-790q433 -734 416 -790);"/>
                    <Edge cubics="!393 -774(;383,-777 379,-788 376,-797q393 -774Q383 -777q376 -797);"/>
                    <Edge cubics="!289 -745(;289,-737 287,-729 283,-723q289 -745Q289 -732q283 -723);"/>
                    <Edge cubics="!283 -723(;279,-716 271,-712 263,-714q283 -723Q276 -711q263 -714);"/>
                    <Edge cubics="!263 -714(;256,-716 251,-723 250,-730q263 -714Q252 -717q250 -730);"/>
                    <Edge cubics="!198 -724(;161,-733 134,-766 121,-802q198 -724Q144 -737q121 -802);"/>
                    <Edge cubics="!121 -802(;109,-838 108,-877 108,-915q121 -802Q108 -841q108 -915);"/>
                    <Edge cubics="!93 -1325(;88,-1370 85,-1414 86,-1459q93 -1325Q85 -1400q86 -1459);"/>
                    <Edge cubics="!86 -1459(;89,-1571 112,-1682 136,-1792q86 -1459Q89 -1577q136 -1792);"/>
                    <Edge cubics="!-204 -1727(;-200,-1696 -202,-1664 -200,-1632q-204 -1727Q-200 -1696q-200 -1632);"/>
                    <Edge cubics="!-200 -1632(;-198,-1601 -193,-1571 -191,-1540q-200 -1632Q-198 -1601q-191 -1540);"/>
                    <Edge cubics="!-191 -1540(;-182,-1400 -228,-1262 -274,-1129q-191 -1540Q-185 -1446q-212 -1332Q-229 -1259q-274 -1129);"/>
                    <Edge cubics="!-274 -1129(;-303,-1046 -332,-962 -361,-879q-274 -1129 -361 -879);"/>
                    <Edge cubics="!54 -1820(;21,-1821 -6,-1821 -28,-1821q54 -1820Q5 -1821q-28 -1821);"/>
                    <Edge cubics="!-209 -1754(;-206,-1744 -205,-1735 -204,-1727q-209 -1754Q-205 -1739q-204 -1727);"/>
                    <Edge cubics="!-206 -1789(;-206,-1789 -209,-1754 -209,-1754q-206 -1789 -209 -1754);"/>
                    <Edge cubics="!-213 -1825(;-208,-1819 -205,-1807 -206,-1789q-213 -1825Q-205 -1816q-206 -1789);"/>
                    <Edge cubics="!-28 -1821(;-93,-1822 -155,-1823 -213,-1825q-28 -1821Q-126 -1822q-213 -1825);"/>
                    <Edge cubics="!96 -1812(;81,-1815 67,-1818 54,-1820q96 -1812Q74 -1817q54 -1820);"/>
                    <Edge cubics="!136 -1792(;137,-1796 138,-1800 139,-1804q136 -1792Q137 -1798q139 -1804);"/>
                    <Edge cubics="!108 -1264(;101,-1280 96,-1300 93,-1325q108 -1264Q98 -1288q93 -1325);"/>
                    <Edge cubics="!139 -1804(;126,-1805 112,-1808 96,-1812q139 -1804Q120 -1806q96 -1812);"/>
                    <Edge cubics="!304 -770(;299,-771 293,-772 288,-773q304 -770Q296 -771q288 -773);"/>
                    <Edge cubics="!288 -773(;289,-763 290,-754 289,-745q288 -773Q290 -758q289 -745);"/>
                    <Edge cubics="!250 -730(;233,-721 215,-719 198,-724q250 -730Q224 -717q198 -724);"/>
                    <Edge cubics="!416 -790(;415,-786 412,-782 409,-779q416 -790Q414 -784q409 -779);"/>
                    <Edge cubics="!409 -779(;404,-774 399,-773 393,-774q409 -779Q402 -772q393 -774);"/>
                    <Edge cubics="!376 -797(;374,-803 372,-809 370,-816q376 -797Q373 -806q370 -816);"/>
                    <Edge cubics="!370 -816(;365,-807 359,-798 352,-790q370 -816Q363 -802q352 -790);"/>
                    <Edge cubics="!352 -790(;337,-775 321,-769 304,-770q352 -790Q330 -768q304 -770);"/>
                    <Edge cubics="!-361 -879(;-364,-872 -366,-865 -368,-858q-361 -879Q-365 -868q-368 -858);"/>
                    <Edge cubics="!-368 -858(;-355,-858 -343,-858 -332,-859q-368 -858Q-348 -858q-332 -859);"/>
                    <Edge cubics="!108 -915(;108,-915 108,-1264 108,-1264q108 -915 108 -1264);"/>
                    <Edge cubics="!-89 -2045(;-90,-2044 -90,-2043 -91,-2042q-89 -2045Q-90 -2043q-91 -2042);"/>
                    <Edge cubics="!96 -2047(;96,-2047 -89,-2045 -89,-2045q96 -2047 -89 -2045);"/>
                    <Edge cubics="!-302 -2041(;-302,-2041 -307,-2041 -307,-2041q-302 -2041 -307 -2041);"/>
                    <Edge cubics="!-303 -2020(;-303,-2028 -303,-2035 -302,-2041q-303 -2020Q-303 -2032q-302 -2041);"/>
                    <Edge cubics="!-307 -2041(;-307,-2035 -306,-2028 -303,-2020q-307 -2041Q-307 -2032q-303 -2020);"/>
                    <Edge cubics="!200 -1942(;200,-1942 210,-2022 210,-2022q200 -1942 210 -2022);"/>
                    <Edge cubics="!178 -1947(;186,-1946 193,-1944 200,-1942q178 -1947Q190 -1945q200 -1942);"/>
                    <Edge cubics="!210 -2022(;183,-2035 151,-2044 113,-2047q210 -2022Q170 -2042q113 -2047);"/>
                    <Edge cubics="!14 -543(;7,-543 1,-543 -6,-543q14 -543Q4 -543q-6 -543);"/>
                    <Edge cubics="!34 -543(;27,-543 21,-543 14,-543q34 -543Q24 -543q14 -543);"/>
                    <Edge cubics="!433 -734(;314,-612 174,-548 14,-543q433 -734Q254 -551q14 -543);"/>
                    <Edge cubics="!-331 -742(;-331,-742 -453,-742 -453,-742q-331 -742 -453 -742);"/>
                  </edges>
                </DOMShape>
                <DOMSymbolInstance libraryItemName="Assets/Bottle Assets copy/sodabottle" centerPoint3DX="0.25" centerPoint3DY="-0.05">
                  <matrix>
                    <Matrix a="0.7623291015625" d="0.7623291015625" tx="0.25" ty="-0.05"/>
                  </matrix>
                  <transformationPoint>
                    <Point x="-0.2" y="0.15"/>
                  </transformationPoint>
                </DOMSymbolInstance>
                <DOMSymbolInstance libraryItemName="Assets/Bottle Assets copy/sodabottletint" centerPoint3DX="-0.4" centerPoint3DY="0.55">
                  <matrix>
                    <Matrix a="0.7623291015625" d="0.7623291015625" tx="-0.4" ty="0.55"/>
                  </matrix>
                  <transformationPoint>
                    <Point x="0.05"/>
                  </transformationPoint>
                </DOMSymbolInstance>
                <DOMSymbolInstance libraryItemName="Assets/CLabelAssets/labelcolor" centerPoint3DY="-10.75">
                  <matrix>
                    <Matrix ty="-10.75"/>
                  </matrix>
                  <transformationPoint>
                    <Point/>
                  </transformationPoint>
                </DOMSymbolInstance>
                <DOMSymbolInstance libraryItemName="Assets/CLabelAssets/sodatext" centerPoint3DX="1.6" centerPoint3DY="-6.75">
                  <matrix>
                    <Matrix a="0.7623291015625" d="0.7623291015625" tx="1.6" ty="-6.75"/>
                  </matrix>
                  <transformationPoint>
                    <Point/>
                  </transformationPoint>
                </DOMSymbolInstance>
              </elements>
            </DOMFrame>
          </frames>
        </DOMLayer>
      </layers>
    </DOMTimeline>
  </timeline>
</DOMSymbolItem>